{
	"animations": [
		{
			"offsets": [
				88,
				10
			],
			"loop": false,
			"fps": 24,
			"anim": "singLEFT",
			"indices": [],
			"name": "bf left0"
		},
		{
			"offsets": [
				56,
				11
			],
			"loop": false,
			"fps": 24,
			"anim": "singDOWN",
			"indices": [],
			"name": "bf down0"
		},
		{
			"offsets": [
				42,
				35
			],
			"loop": false,
			"fps": 24,
			"anim": "singUP",
			"indices": [],
			"name": "bf up0"
		},
		{
			"offsets": [
				47,
				14
			],
			"loop": false,
			"fps": 24,
			"anim": "singRIGHT",
			"indices": [],
			"name": "bf right0"
		},
		{
			"offsets": [
				86,
				11
			],
			"loop": false,
			"fps": 24,
			"anim": "singLEFTmiss",
			"indices": [],
			"name": "bf left miss"
		},
		{
			"offsets": [
				76,
				21
			],
			"loop": false,
			"fps": 24,
			"anim": "singDOWNmiss",
			"indices": [],
			"name": "bf down miss"
		},
		{
			"offsets": [
				34,
				34
			],
			"loop": false,
			"fps": 24,
			"anim": "singUPmiss",
			"indices": [],
			"name": "bf up miss"
		},
		{
			"offsets": [
				63,
				15
			],
			"loop": false,
			"fps": 24,
			"anim": "singRIGHTmiss",
			"indices": [],
			"name": "bf right miss"
		},
		{
			"offsets": [
				0,
				0
			],
			"loop": false,
			"fps": 24,
			"anim": "idle",
			"indices": [],
			"name": "bf idle"
		}
	],
	"no_antialiasing": false,
	"image": "characters/bf_handsome",
	"position": [
		0,
		350
	],
	"healthicon": "bf-object",
	"flip_x": true,
	"healthbar_colors": [
		49,
		176,
		209
	],
	"camera_position": [
		0,
		0
	],
	"sing_duration": 4,
	"scale": 1
}